pego/__init__.py
pego/pego.py
pego-0.1.dev0.dist-info/DESCRIPTION.rst
pego-0.1.dev0.dist-info/METADATA
pego-0.1.dev0.dist-info/RECORD
pego-0.1.dev0.dist-info/WHEEL
pego-0.1.dev0.dist-info/metadata.json
pego-0.1.dev0.dist-info/top_level.txt
