Metadata-Version: 2.0
Name: pego
Version: 0.1.dev0
Summary: Easy-to-use Parsing library
Home-page: https://github.com/kurtbrose/pego
Author: Kurt Rose
Author-email: kurt@kurtrose.com
License: BSD
Platform: any
Classifier: Intended Audience :: Developers
Classifier: Programming Language :: Python :: 2.7
Classifier: Programming Language :: Python :: 3.6
